gpe_tokenizer/__init__.py
gpe_tokenizer/models/merges.pkl
gpe_tokenizer/models/vocab.pkl
gpe_tokenizer/models/vocab_re.pkl
gpe_tokenizer/tokenizer.py
gpe_tokenizer/trainer/__init__.py
gpe_tokenizer/trainer/dataloader.py
gpe_tokenizer/trainer/training_pipeline.py
gpe_tokenizer-0.1.6.4.dist-info/METADATA
gpe_tokenizer-0.1.6.4.dist-info/WHEEL
gpe_tokenizer-0.1.6.4.dist-info/RECORD
